{
  "builds": [
    {
      "cohort_number": 3,
      "cohort_location": "Bangalore",
      "product_name": "A Tree for You",
      "participant_name": "Samson David",
      "description": "Rent a fruit tree for the season and have its harvest shipped to your door.",
      "url": "https://justbuild.orangecaterpillar.com/showcase/a-tree-for-you.html"
    },
    {
      "cohort_number": 3,
      "cohort_location": "Bangalore",
      "product_name": "Daily Dabba",
      "participant_name": "Samson David",
      "description": "A home-cooked tiffin subscription where you choose every meal, delivered daily.",
      "url": "https://justbuild.orangecaterpillar.com/showcase/daily-dabba.html"
    },
    {
      "cohort_number": 3,
      "cohort_location": "Bangalore",
      "product_name": "Zevar",
      "participant_name": "Samson David",
      "description": "Fine jewellery with a live, itemised price breakup and lifetime buyback.",
      "url": "https://justbuild.orangecaterpillar.com/showcase/zevar.html"
    },
    {
      "cohort_number": 3,
      "cohort_location": "Bangalore",
      "product_name": "Crumbs",
      "participant_name": "Samson David",
      "description": "A neighbourhood Indian bakery for fresh daily bakes and made-to-order cakes.",
      "url": "https://justbuild.orangecaterpillar.com/showcase/crumbs.html"
    }
  ]
}
